pyMAdot2
