Metadata-Version: 2.1
Name: pyMAdot2
Version: 0.0.3
Summary: Python library for MA Lighting dot2 console
Home-page: https://github.com/elektr0nisch/pyMAdot2
Author: Linus Groschke
Author-email: linus@elektronisch.dev
License: MIT
Platform: any
Classifier: Intended Audience :: Developers
Classifier: Operating System :: OS Independent
Classifier: Programming Language :: Python
Classifier: Programming Language :: Python :: 3
Classifier: Programming Language :: Python :: 3.9
Classifier: Programming Language :: Python :: 3.10
Classifier: Topic :: Software Development :: Libraries :: Python Modules
Requires-Python: >=3.9
License-File: LICENSE
